cudart.cp310-win_amd64.pyd
cudart-1.0.1.dist-info/LICENSE
cudart-1.0.1.dist-info/METADATA
cudart-1.0.1.dist-info/WHEEL
cudart-1.0.1.dist-info/top_level.txt
cudart-1.0.1.dist-info/RECORD
