Metadata-Version: 2.1
Name: cudart
Version: 1.0.1
Summary: Tricks your system to use the most powerful GPU
Home-page: https://github.com/szabolcsdombi/cudart/
Author: Szabolcs Dombi
Author-email: szabolcs@szabolcsdombi.com
License: MIT
Keywords: gpu
Platform: windows
License-File: LICENSE
